{  
   "usernames":[  
      {  
         "username":"aditya@spinsci.com",
         "password":"adi"
      },
      {  
         "username":"kumar@spinsci.com",
         "password":"KumarRaja"
      },
      {  
         "username":"naveen@spinsci.com",
         "password":"Naveen"
      },
      {  
         "username":"pradyumna@spinsci.com",
         "password":"Pradyumna"
      },
      {  
         "username":"priyanka@spinsci.com",
         "password":"Priyanka"
      },
      {  
         "username":"raj@spinsci.com",
         "password":"Rajasekhar"
      },
      {  
         "username":"ravi@spinsci.com",
         "password":"Ravi@123"
      },
      {  
         "username":"mohiddin@spinsci.com",
         "password":"mohiddin"
      },
      {  
         "username":"srikanth.inkollu@spinsci.com",
         "password":"Srikanth@14"
      },
      {  
         "username":"james@spinsci.com",
         "password":"James@13"
      },
      {  
         "username":"sunder@spinsci.com",
         "password":"Sunder@14"
      },
      {  
         "username":"vineet@spinsci.com",
         "password":"vini"
      },
      {  
         "username":"pradeep@spinsci.com",
         "password":"pradeep"
      },
      {  
         "username":"kishore@spinsci.com",
         "password":"Kishore"
      }
   ]
}